[
  {
    "image": {
      "_type": "image",
      "attribution": "Mid Journey",
      "caption": "Its not rocket science",
      "asset": {
        "_type": "reference",
        "_ref": "image-14a74f81cf79b20391fcb7afebf2549a6213c4ba-720x480-png"
      }
    },
    "_id": "drafts.16e44988-6b58-4cdd-912a-b656884bdf96",
    "publishedDate": "2023-03-30",
    "title": "This is the first title of the month ",
    "slug": {
      "current": "first-post",
      "_type": "slug"
    },
    "description": "Lorem ipsum dolor sit amet, consectetur adipiscing elit. Proin commodo, tortor sed laoreet euismod, diam risus dictum elit, vitae mollis dolor riyu."
  },
  {
    "_id": "b4ff5416-9d9b-4006-9f27-236f404026a1",
    "publishedDate": "2023-03-21",
    "title": "The Fifth Post",
    "slug": {
      "current": "the-fifth-post",
      "_type": "slug"
    },
    "description": "Nunc et varius lacus. Aliquam mattis ipsum dolor. In mauris quam, malesuada sit amet nulla sed, lobortis molestie nisi. Aenean gravida vestibulum augue sit amet volutpat.",
    "image": {
      "asset": {
        "_ref": "image-8e61526d46baaf68785cd5e36f0f20675dfefb45-720x480-png",
        "_type": "reference"
      },
      "_type": "image",
      "caption": "Unknown City"
    }
  },
  {
    "_id": "d98cf0d0-3390-42d2-826f-994dc5511e61",
    "publishedDate": "2023-03-14",
    "title": "The Fourth Post",
    "slug": {
      "current": "the-fourth-post",
      "_type": "slug"
    },
    "description": "The Fourth Post Lorem ipsum dolor sit amet, consectetur adipiscing elit. Proin commodo, tortor sed laoreet euismod, diam risus dictum elit, vitae mollis dolor risus luctus dolor. Suspendisse rhoncus libero nunc, et sagittis ligula sodales ut. Morbi bibendum ut lorem commodo auctor. Sed et ipsum non nisl scelerisque efficitur. In gravida dui a quam rutrum ullamcorper. Suspendisse vel ligula sapien. Donec quis tempor ex, nec tempor ligula.",
    "image": {
      "asset": {
        "_ref": "image-c5e5c40e3b9f8741e4f68d794e69564c0e6d4793-720x480-png",
        "_type": "reference"
      },
      "_type": "image",
      "caption": "Night Place"
    }
  },
  {
    "title": "The Third Post",
    "slug": {
      "current": "the-third-post",
      "_type": "slug"
    },
    "description": "The Third Post is Lorem ipsum dolor sit amet, consectetur adipiscing elit. Proin commodo, tortor sed laoreet euismod, diam risus dictum elit, vitae mollis dolor risus luctus dolor. Suspendisse rhoncus libero nunc, et sagittis ligula sodales ut. Morbi bibendum ut lorem commodo auctor. Sed et ipsum non nisl scelerisque efficitur. In gravida dui a quam rutrum ullamcorper. Suspendisse vel ligula sapien. Donec quis tempor ex, nec tempor ligula.",
    "image": {
      "_type": "image",
      "caption": "A Lone Lone Lone",
      "asset": {
        "_ref": "image-08762d8dfd9936fde474140baadc4292a64a7f98-720x480-png",
        "_type": "reference"
      }
    },
    "_id": "d760cdda-6d19-423b-b8c7-22a23bbffe54",
    "publishedDate": "2023-03-07"
  },
  {
    "description": "The Second Post is Lorem ipsum dolor sit amet, consectetur adipiscing elit. Proin commodo, tortor sed laoreet euismod, diam risus dictum elit, vitae mollis dolor risus luctus dolor. Suspendisse rhoncus libero nunc, et sagittis ligula sodales ut. Morbi bibendum ut lorem commodo auctor. Sed et ipsum non nisl scelerisque efficitur. In gravida dui a quam rutrum ullamcorper. Suspendisse vel ligula sapien. Donec quis tempor ex, nec tempor ligula.",
    "image": {
      "_type": "image",
      "caption": "The Samurai",
      "asset": {
        "_ref": "image-d10c73965a2330cd5e4ff5e5da8ea2c63a45302b-832x480-png",
        "_type": "reference"
      }
    },
    "_id": "b0e5d39f-f469-4e5a-a2d1-93755525239c",
    "publishedDate": "2023-03-01",
    "title": "The Second Post",
    "slug": {
      "_type": "slug",
      "current": "the-second-post"
    }
  }
]
